spelunker/__init__.py
spelunker/_version.py
spelunker/spelunker.py
spelunker-1.1.18.dist-info/LICENSE
spelunker-1.1.18.dist-info/METADATA
spelunker-1.1.18.dist-info/WHEEL
spelunker-1.1.18.dist-info/top_level.txt
spelunker-1.1.18.dist-info/RECORD
