Metadata-Version: 2.1
Name: spelunker
Version: 1.1.18
Summary: spelunker: a library to extract guidestar data and observe technical and stellar events
Home-page: https://github.com/GalagaBits/JWST-FGS-Spelunker
Author: Derod Deal
Author-email: dealderod@ufl.edu
License: MIT
Keywords: guidestars
Requires-Python: <3.12
License-File: LICENSE
Requires-Dist: numpy
Requires-Dist: scipy
Requires-Dist: pandas
Requires-Dist: jwst
Requires-Dist: astroquery
Requires-Dist: astropy
Requires-Dist: astroplan
Requires-Dist: matplotlib
Requires-Dist: ray
Requires-Dist: tqdm
Requires-Dist: wheel
